pyiddidf/__init__.py
pyiddidf/exceptions.py
pyiddidf/settings.py
pyiddidf/idd/__init__.py
pyiddidf/idd/objects.py
pyiddidf/idd/processor.py
pyiddidf/idf/__init__.py
pyiddidf/idf/objects.py
pyiddidf/idf/processor.py
pyiddidf-0.7.dist-info/DESCRIPTION.rst
pyiddidf-0.7.dist-info/METADATA
pyiddidf-0.7.dist-info/RECORD
pyiddidf-0.7.dist-info/WHEEL
pyiddidf-0.7.dist-info/metadata.json
pyiddidf-0.7.dist-info/top_level.txt
