Metadata-Version: 2.0
Name: pyiddidf
Version: 0.7
Summary: EnergyPlus idd/idf manipulation in Python.
Home-page: https://github.com/myoldmopar/py-idd-idf
Author: Edwin Lee
Author-email: leeed2001@gmail.com
License: UNKNOWN
Keywords: cli energyplus
Platform: UNKNOWN
Classifier: Intended Audience :: Developers
Classifier: Topic :: Utilities
Classifier: License :: Public Domain
Classifier: Natural Language :: English
Classifier: Operating System :: OS Independent
Classifier: Programming Language :: Python
Provides-Extra: test
Requires-Dist: coverage; extra == 'test'
Requires-Dist: coveralls; extra == 'test'
Requires-Dist: unittest; extra == 'test'
